boxgen/__init__.py
boxgen-1.0.4.dist-info/METADATA
boxgen-1.0.4.dist-info/RECORD
boxgen-1.0.4.dist-info/WHEEL
boxgen-1.0.4.dist-info/entry_points.txt
boxgen-1.0.4.dist-info/top_level.txt
