Metadata-Version: 2.1
Name: boxgen
Version: 1.0.4
Summary: Generate box designs, to print on card stock and cut out.
Home-page: https://github.com/duckinator/boxgen
Author: Ellen Marie Dash
Author-email: me@duckie.co
License: MIT
Platform: UNKNOWN
Classifier: Programming Language :: Python :: 3
Classifier: License :: OSI Approved :: MIT License
Classifier: Operating System :: OS Independent
Requires-Python: ~=3.6
Requires-Dist: svgwrite (<1.2,>=1.1.12)
